{"displayFieldName":"","fieldAliases":{"FID":"FID","Id":"Id","name":"name","flg":"flg","height":"height"},"geometryType":"esriGeometryPolyline","spatialReference":{"wkid":4326,"latestWkid":4326},"fields":[{"name":"FID","type":"esriFieldTypeOID","alias":"FID"},{"name":"Id","type":"esriFieldTypeInteger","alias":"Id"},{"name":"name","type":"esriFieldTypeString","alias":"name","length":254},{"name":"flg","type":"esriFieldTypeDouble","alias":"flg"},{"name":"height","type":"esriFieldTypeDouble","alias":"height"}],"features":[{"attributes":{"FID":0,"Id":0,"name":"4-0-2114","flg":0.5,"height":12.43},"geometry":{"paths":[[[120.08486998543685,30.302181457446817],[120.08487077273362,30.302107666573765],[120.0849506097899,30.302108753463209],[120.08494984198077,30.302114453899851],[120.08495924093343,30.302113970404669],[120.08495773756549,30.302184973169322],[120.08486998543685,30.30218145744681]]]}}]}