{"displayFieldName":"","fieldAliases":{"FID":"FID","Id":"Id","name":"name","flg":"flg","height":"height"},"geometryType":"esriGeometryPolyline","spatialReference":{"wkid":4326,"latestWkid":4326},"fields":[{"name":"FID","type":"esriFieldTypeOID","alias":"FID"},{"name":"Id","type":"esriFieldTypeInteger","alias":"Id"},{"name":"name","type":"esriFieldTypeString","alias":"name","length":254},{"name":"flg","type":"esriFieldTypeDouble","alias":"flg"},{"name":"height","type":"esriFieldTypeDouble","alias":"height"}],"features":[{"attributes":{"FID":0,"Id":0,"name":"4-0-2115","flg":0.5,"height":12.43},"geometry":{"paths":[[[120.08497486186137,30.302182366218435],[120.08506128200807,30.3021823978203],[120.08506070283579,30.302107125430698],[120.08498174953594,30.30210780173206],[120.08498250064324,30.302114044980573],[120.08497657675807,30.302113912913693],[120.08497486186137,30.302182366218435]]]}}]}