{
  "displayFieldName": "",
  "fieldAliases": {
    "FID": "FID",
    "Shape_Leng": "Shape_Leng",
    "height": "height",
    "flg": "flg",
    "name": "name"
  },
  "geometryType": "esriGeometryPolyline",
  "spatialReference": { "wkid": 4326, "latestWkid": 4326 },
  "fields": [
    { "name": "FID", "type": "esriFieldTypeOID", "alias": "FID" },
    {
      "name": "Shape_Leng",
      "type": "esriFieldTypeDouble",
      "alias": "Shape_Leng"
    },
    { "name": "height", "type": "esriFieldTypeSingle", "alias": "height" },
    { "name": "flg", "type": "esriFieldTypeSingle", "alias": "flg" },
    {
      "name": "name",
      "type": "esriFieldTypeString",
      "alias": "name",
      "length": 254
    }
  ],
  "features": [
    {
      "attributes": {
        "FID": 0,
        "Shape_Leng": 0.00039600048342800003,
        "height": 17.690000534057617,
        "flg": 3.8599998950958252,
        "name": "4-2-1233"
      },
      "geometry": {
        "paths": [
          [
            [120.08403661900002, 30.301260021000076],
            [120.0841405760001, 30.30126001800005],
            [120.084140574, 30.301165818000072],
            [120.08403661700004, 30.301166135000074],
            [120.08403661900002, 30.301259959000049],
            [120.08403661900002, 30.301260021000076]
          ]
        ]
      }
    }
  ]
}
