{"displayFieldName":"","fieldAliases":{"FID":"FID","Id":"Id","name":"name","flg":"flg","height":"height"},"geometryType":"esriGeometryPolyline","spatialReference":{"wkid":4326,"latestWkid":4326},"fields":[{"name":"FID","type":"esriFieldTypeOID","alias":"FID"},{"name":"Id","type":"esriFieldTypeInteger","alias":"Id"},{"name":"name","type":"esriFieldTypeString","alias":"name","length":254},{"name":"flg","type":"esriFieldTypeDouble","alias":"flg"},{"name":"height","type":"esriFieldTypeDouble","alias":"height"}],"features":[{"attributes":{"FID":0,"Id":0,"name":"4-6-2615","flg":3.8599999999999999,"height":33.100000000000001},"geometry":{"paths":[[[120.08520236600022,30.301863355000126],[120.08524910400013,30.301864397000145],[120.08525123900017,30.301792297000201],[120.08520450000015,30.301791255000175],[120.08520236600022,30.301863355000123]]]}}]}